cpu15/verilog/ram_wb.v


module ram_wb(CLK_WB, RAM_ADDR, RAM_IN, RAM_WEN, RAM_0, RAM_1, RAM_2, RAM_3,
              RAM_4, RAM_5, RAM_6, RAM_7, IO64_OUT);

    input         CLK_WB;
    input [7:0]   RAM_ADDR;
    input [15:0]  RAM_IN;
    input         RAM_WEN;
    output [15:0] RAM_0;
    output [15:0] RAM_1;
    output [15:0] RAM_2;
    output [15:0] RAM_3;
    output [15:0] RAM_4;
    output [15:0] RAM_5;
    output [15:0] RAM_6;
    output [15:0] RAM_7;
    output [15:0] IO64_OUT;

    reg [15:0]    RAM_0 = 0;
    reg [15:0]    RAM_1 = 0;
    reg [15:0]    RAM_2 = 0;
    reg [15:0]    RAM_3 = 0;
    reg [15:0]    RAM_4 = 0;
    reg [15:0]    RAM_5 = 0;
    reg [15:0]    RAM_6 = 0;
    reg [15:0]    RAM_7 = 0;
    reg [15:0]    IO64_OUT = 0;

    always@(posedge CLK_WB) begin

        if(RAM_WEN) begin

            case(RAM_ADDR)
                8'h0: RAM_0 <= RAM_IN;
                8'h1: RAM_1 <= RAM_IN;
                8'h2: RAM_2 <= RAM_IN;
                8'h3: RAM_3 <= RAM_IN;
                8'h4: RAM_4 <= RAM_IN;
                8'h5: RAM_5 <= RAM_IN;
                8'h6: RAM_6 <= RAM_IN;
                8'h7: RAM_7 <= RAM_IN;
                8'h40: IO64_OUT <= RAM_IN;
            endcase // case (N_RAM)
            
        end // if (RAM_WEN)
        
    end // always@ (posedge CLK_WB)

endmodule // ram_wb

cpu15/verilog/reg_wb.v


module reg_wb(CLK_WB, RESET_N, N_REG, REG_IN, REG_WEN, REG_0, REG_1, REG_2,
              REG_3, REG_4, REG_5, REG_6, REG_7);

    input         CLK_WB;
    input         RESET_N;
    input [2:0]   N_REG;
    input [15:0]  REG_IN;
    input         REG_WEN;
    output [15:0] REG_0;
    output [15:0] REG_1;
    output [15:0] REG_2;
    output [15:0] REG_3;
    output [15:0] REG_4;
    output [15:0] REG_5;
    output [15:0] REG_6;
    output [15:0] REG_7;

    reg [15:0]    REG_0;
    reg [15:0]    REG_1;
    reg [15:0]    REG_2;
    reg [15:0]    REG_3;
    reg [15:0]    REG_4;
    reg [15:0]    REG_5;
    reg [15:0]    REG_6;
    reg [15:0]    REG_7;

    always@(posedge CLK_WB) begin

        if(RESET_N == 1'b0) begin
            REG_0 <= 0;
            REG_1 <= 0;
            REG_2 <= 0;
            REG_3 <= 0;
            REG_4 <= 0;
            REG_5 <= 0;
            REG_6 <= 0;
            REG_7 <= 0;
        end else begin

            if(REG_WEN) begin

                case(N_REG)
                    3'h0: REG_0 <= REG_IN;
                    3'h1: REG_1 <= REG_IN;
                    3'h2: REG_2 <= REG_IN;
                    3'h3: REG_3 <= REG_IN;
                    3'h4: REG_4 <= REG_IN;
                    3'h5: REG_5 <= REG_IN;
                    3'h6: REG_6 <= REG_IN;
                    3'h7: REG_7 <= REG_IN;
                endcase // case (N_REG)
                
            end // if (REG_WEN)

        end // else: !if(RESET_N)
        
    end // always@ (posedge CLK_WB)
    
endmodule // reg_wb

cpu15/verilog/exec.v


module exec(CLK_EX, RESET_N, OP_CODE, REG_A, REG_B, OP_DATA, RAM_OUT, P_COUNT,
            REG_IN, RAM_IN, REG_WEN, RAM_WEN);

    input         CLK_EX;
    input         RESET_N;
    input [3:0]   OP_CODE;
    input [15:0]  REG_A;
    input [15:0]  REG_B;
    input [7:0]   OP_DATA;
    input [15:0]  RAM_OUT;
    output [7:0]  P_COUNT;
    output [15:0] REG_IN;
    output [15:0] RAM_IN;
    output        REG_WEN;
    output        RAM_WEN;

    reg [7:0]     P_COUNT = 0;
    reg [15:0]    REG_IN = 0;
    reg [15:0]    RAM_IN = 0;
    reg           REG_WEN = 0;
    reg           RAM_WEN = 0;
    reg           CMP_FLAG = 0;
    
    always@(posedge CLK_EX) begin

        if(RESET_N == 1'b0) begin
            P_COUNT <= 0;
            CMP_FLAG <= 0;
        end else begin
            
            case(OP_CODE)
                
                4'h0: begin     // MOV
                    REG_IN  <= REG_B;
                    REG_WEN <= 1;
                    RAM_WEN <= 0;
                    P_COUNT <= P_COUNT + 8'h01;
                end

                4'h1: begin     // ADD
                    REG_IN  <= REG_A + REG_B;
                    REG_WEN <= 1;
                    RAM_WEN <= 0;
                    P_COUNT <= P_COUNT + 8'h01;
                end

                4'h2: begin     // SUB
                    REG_IN  <= REG_A - REG_B;
                    REG_WEN <= 1;
                    RAM_WEN <= 0;
                    P_COUNT <= P_COUNT + 8'h01;
                end

                4'h3: begin     // AND
                    REG_IN  <= REG_A & REG_B;
                    REG_WEN <= 1;
                    RAM_WEN <= 0;
                    P_COUNT <= P_COUNT + 8'h01;
                end

                4'h4: begin     // OR
                    REG_IN  <= REG_A | REG_B;
                    REG_WEN <= 1;
                    RAM_WEN <= 0;
                    P_COUNT <= P_COUNT + 8'h01;
                end

                4'h5: begin     // SL
                    REG_IN  <= (REG_A << 1);
                    REG_WEN <= 1;
                    RAM_WEN <= 0;
                    P_COUNT <= P_COUNT + 8'h01;
                end

                4'h6: begin     // SR
                    REG_IN  <= (REG_A >> 1);
                    REG_WEN <= 1;
                    RAM_WEN <= 0;
                    P_COUNT <= P_COUNT + 8'h01;
                end

                4'h7: begin     // SRA
                    REG_IN  <= ((REG_A >> 1) | REG_A & 16'h8000);
                    REG_WEN <= 1;
                    RAM_WEN <= 0;
                    P_COUNT <= P_COUNT + 8'h01;
                end 

                4'h8: begin     // LDL
                    REG_IN  <= {REG_A[15:8], OP_DATA};
                    REG_WEN <= 1;
                    RAM_WEN <= 0;
                    P_COUNT <= P_COUNT + 8'h01;
                end

                4'h9: begin     // LDH
                    REG_IN  <= {OP_DATA, REG_A[7:0]};
                    REG_WEN <= 1;
                    RAM_WEN <= 0;
                    P_COUNT <= P_COUNT + 8'h01;
                end

                4'hA: begin     // CMP
                    CMP_FLAG <= REG_A == REG_B ? 1'b1 : 1'b0;
                    REG_WEN  <= 0;
                    RAM_WEN  <= 0;
                    P_COUNT <= P_COUNT + 8'h01;
                end

                4'hB: begin     // JE
                    REG_WEN <= 0;
                    RAM_WEN <= 0;
                    P_COUNT <= CMP_FLAG ? OP_DATA : P_COUNT + 8'h01;
                end

                4'hC: begin     // JMP
                    REG_WEN <= 0;
                    RAM_WEN <= 0;
                    P_COUNT <= OP_DATA;
                end

                4'hD: begin     // LD
                    REG_IN  <= RAM_OUT;
                    REG_WEN <= 1;
                    RAM_WEN <= 0;
                    P_COUNT <= P_COUNT + 8'h01;
                end

                4'hE: begin     // ST
                    RAM_IN  <= REG_A;
                    REG_WEN <= 0;
                    RAM_WEN <= 1;
                    P_COUNT <= P_COUNT + 8'h01;
                end

                4'hF: begin     // HLT
                    REG_WEN <= 0;
                    RAM_WEN <= 0;
                end
                
            endcase // case (OP_CODE)

        end // else: !if(RESET_N)
        
    end // always@ (posedge CLK_EX)

endmodule // exec

cpu15/verilog/ram_dc.v


module ram_dc(CLK_DC, RAM_AD_IN, RAM_0, RAM_1, RAM_2, RAM_3, RAM_4, RAM_5,
              RAM_6, RAM_7, IO65_IN, RAM_AD_OUT, RAM_OUT);

    input         CLK_DC;
    input [7:0]   RAM_AD_IN;
    input [15:0]  RAM_0;
    input [15:0]  RAM_1;
    input [15:0]  RAM_2;
    input [15:0]  RAM_3;
    input [15:0]  RAM_4;
    input [15:0]  RAM_5;
    input [15:0]  RAM_6;
    input [15:0]  RAM_7;
    input [15:0]  IO65_IN;
    output [7:0]  RAM_AD_OUT;
    output [15:0] RAM_OUT;

    reg [7:0]     RAM_AD_OUT;
    reg [15:0]    RAM_OUT;

    always@(posedge CLK_DC) begin

        RAM_AD_OUT <= RAM_AD_IN;
        
        case(RAM_AD_IN)
            8'h00: RAM_OUT <= RAM_0;
            8'h01: RAM_OUT <= RAM_1;
            8'h02: RAM_OUT <= RAM_2;
            8'h03: RAM_OUT <= RAM_3;
            8'h04: RAM_OUT <= RAM_4;
            8'h05: RAM_OUT <= RAM_5;
            8'h06: RAM_OUT <= RAM_6;
            8'h07: RAM_OUT <= RAM_7;
            8'h40: RAM_OUT <= IO65_IN;
            default: RAM_OUT <= 16'hFFFF;
        endcase
    end
    

endmodule // ram_dc

cpu15/verilog/reg_dc.v


module reg_dc(CLK_DC, N_REG_IN, REG_0, REG_1, REG_2, REG_3, REG_4, REG_5,
              REG_6, REG_7, N_REG_OUT, REG_OUT);

    input         CLK_DC;
    input [2:0]   N_REG_IN;
    input [15:0]  REG_0;
    input [15:0]  REG_1;
    input [15:0]  REG_2;
    input [15:0]  REG_3;
    input [15:0]  REG_4;
    input [15:0]  REG_5;
    input [15:0]  REG_6;
    input [15:0]  REG_7;
    output [2:0]  N_REG_OUT;
    output [15:0] REG_OUT;

    reg [2:0]     N_REG_OUT;
    reg [15:0]    REG_OUT;
    
    always@(posedge CLK_DC) begin

        N_REG_OUT <= N_REG_IN;

        case(N_REG_IN)
            3'b000: REG_OUT <= REG_0;
            3'b001: REG_OUT <= REG_1;
            3'b010: REG_OUT <= REG_2;
            3'b011: REG_OUT <= REG_3;
            3'b100: REG_OUT <= REG_4;
            3'b101: REG_OUT <= REG_5;
            3'b110: REG_OUT <= REG_6;
            3'b111: REG_OUT <= REG_7;
        endcase // case (N_REG_IN)
    end

endmodule // reg_dc

cpu15/verilog/decode.v


module decode(CLK_DC, PROM_OUT, OP_CODE, OP_DATA);

    input        CLK_DC;
    input [14:0] PROM_OUT;
    output [3:0] OP_CODE;
    output [7:0] OP_DATA;

    reg [3:0]    OP_CODE;
    reg [7:0]    OP_DATA;

    always@(posedge CLK_DC) begin
        OP_CODE <= PROM_OUT[14:11];
        OP_DATA <= PROM_OUT[7:0];
    end

endmodule // decode

cpu15/verilog/fetch.v


module fetch(CLK_FT, P_COUNT, PROM_OUT);

    input         CLK_FT;
    input [7:0]   P_COUNT;
    output [14:0] PROM_OUT;
    
    reg [14:0]    PROM_OUT;
    reg [15*16-1:0] mem = {15'b1001_0000_0000_000, // ldh Reg0, 0
                           15'b1000_0000_0000_000, // ldl Reg0, 0
                           15'b1001_0010_0000_000, // ldh Reg1, 0
                           15'b1000_0010_0000_001, // ldl Reg1, 1
                           15'b1001_0100_0000_000, // ldh Reg2, 0
                           15'b1000_0100_0000_000, // ldl Reg2, 0
                           15'b1001_0110_0000_000, // ldh Reg3, 0
                           15'b1000_0110_0001_010, // ldl Reg3, 10
                           15'b0001_0100_0100_000, // add Reg2, Reg1
                           15'b0001_0000_1000_000, // add Reg0, Reg2
                           15'b1110_0000_1000_000, // st Reg0, 64
                           15'b1010_0100_1100_000, // cmp Reg2, Reg3
                           15'b1011_0000_0001_110, // je 14
                           15'b1100_0000_0001_000, // jmp 8
                           15'b1111_0000_0000_000, // hlt
                           15'b0000_0000_0000_000  // nop
                           };

    always@(posedge CLK_FT) begin
        PROM_OUT <= mem[(15-P_COUNT[3:0]) * 15 +: 15];
        // PROM_OUT <= mem[(8'h10 - (P_COUNT & 8'h0F)) * 15 - 1:
        //                 (8'hF - (P_COUNT & 8'h0F)) * 15];
    end

endmodule // fetch

cpu15/verilog/clock_gen.v


module clock_gen(CLK, CLK_FT, CLK_DC, CLK_EX, CLK_WB);

    input          CLK;
    output         CLK_FT;
    output         CLK_DC;
    output         CLK_EX;
    output         CLK_WB;

    reg            CLK_FT = 0;
    reg            CLK_DC = 0;
    reg            CLK_EX = 0;
    reg            CLK_WB = 0;
    reg [1:0]      COUNT = 2'b00;

    always@(posedge CLK) begin

        COUNT <= COUNT + 2'b01;
        
        if(COUNT == 2'b00) begin
            CLK_FT <= 1;
            CLK_DC <= 0;
            CLK_EX <= 0;
            CLK_WB <= 0;
        end 
        else if(COUNT == 2'b01) begin
            CLK_FT <= 0;
            CLK_DC <= 1;
            CLK_EX <= 0;
            CLK_WB <= 0;
        end 
        else if(COUNT == 2'b10) begin
            CLK_FT <= 0;
            CLK_DC <= 0;
            CLK_EX <= 1;
            CLK_WB <= 0;
        end 
        else if(COUNT == 2'b11) begin
            CLK_FT <= 0;
            CLK_DC <= 0;
            CLK_EX <= 0;
            CLK_WB <= 1;
        end
        
    end

endmodule

cpu15/verilog/cpu15.v


module cpu15(CLK, RESET_N, IO65_IN, IO64_OUT);
    
    input         CLK;
    input         RESET_N;
    input [15:0]  IO65_IN;
    output [15:0] IO64_OUT;

    wire          CLK_FT;
    wire          CLK_DC;
    wire          CLK_EX;
    wire          CLK_WB;
    wire [7:0]    P_COUNT;
    wire [14:0]   PROM_OUT;
    wire [3:0]    OP_CODE;
    wire [7:0]    OP_DATA;
    wire [15:0]   REG_0;
    wire [15:0]   REG_1;
    wire [15:0]   REG_2;
    wire [15:0]   REG_3;
    wire [15:0]   REG_4;
    wire [15:0]   REG_5;
    wire [15:0]   REG_6;
    wire [15:0]   REG_7;
    wire [2:0]    N_REG_A;
    wire [2:0]    N_REG_B;
    wire [15:0]   REG_A;
    wire [15:0]   REG_B;
    wire [15:0]   RAM_0;
    wire [15:0]   RAM_1;
    wire [15:0]   RAM_2;
    wire [15:0]   RAM_3;
    wire [15:0]   RAM_4;
    wire [15:0]   RAM_5;
    wire [15:0]   RAM_6;
    wire [15:0]   RAM_7;
    wire [7:0]    RAM_ADDR;
    wire [15:0]   RAM_OUT;
    wire [15:0]   REG_IN;
    wire [15:0]   RAM_IN;
    wire          REG_WEN;
    wire          RAM_WEN;
    
    clock_gen C1(CLK, CLK_FT, CLK_DC, CLK_EX, CLK_WB);
    
    fetch C2(CLK_FT, P_COUNT, PROM_OUT);
    
    decode C3(CLK_DC, PROM_OUT, OP_CODE, OP_DATA);
    
    reg_dc C4(CLK_DC, PROM_OUT[10:8], REG_0, REG_1, REG_2, REG_3, REG_4, REG_5,
              REG_6, REG_7, N_REG_A, REG_A);
    
    reg_dc C5(CLK_DC, PROM_OUT[7:5], REG_0, REG_1, REG_2, REG_3, REG_4, REG_5,
              REG_6, REG_7, N_REG_B, REG_B);
    
    ram_dc C6(CLK_DC, PROM_OUT[7:0], RAM_0, RAM_1, RAM_2, RAM_3, RAM_4, RAM_5,
              RAM_6, RAM_7, IO65_IN, RAM_ADDR, RAM_OUT);
    
    exec C7(CLK_EX, RESET_N, OP_CODE, REG_A, REG_B, OP_DATA, RAM_OUT, P_COUNT,
            REG_IN, RAM_IN, REG_WEN, RAM_WEN);
    
    reg_wb C8(CLK_WB, RESET_N, N_REG_A, REG_IN, REG_WEN, REG_0, REG_1, REG_2,
              REG_3, REG_4, REG_5, REG_6, REG_7);
    
    ram_wb C9(CLK_WB, RAM_ADDR, RAM_IN, RAM_WEN, RAM_0, RAM_1, RAM_2, RAM_3,
              RAM_4, RAM_5, RAM_6, RAM_7, IO64_OUT);

endmodule // cpu15

cpu15/icarus/cpu15_sim.v

module cpu15_sim();

    reg         CLK     = 0;
    reg         RESET_N = 0;
    reg [15:0]  IO65_IN = 16'h0000;
    wire [15:0] IO64_OUT;

    cpu15 C0(CLK, RESET_N, IO65_IN, IO64_OUT);

    initial begin
        $dumpfile("cpu15_sim.vcd");
        $dumpvars(0, cpu15_sim.C0);
        #100 RESET_N <= 1'b1;
        #10000 $finish;
    end

    always begin
        # 10 CLK <= ~CLK;
    end

endmodule // cpu15_sim

cpu15/icarus/cpu15_sim.vcd
$date
	Sun Jan  3 15:45:28 2021
$end
$version
	Icarus Verilog
$end
$timescale
	1s
$end
$scope module cpu15_sim $end
$scope module C0 $end
$var wire 1 ! CLK $end
$var wire 16 " IO65_IN [15:0] $end
$var wire 1 # RESET_N $end
$var wire 1 $ REG_WEN $end
$var wire 16 % REG_IN [15:0] $end
$var wire 16 & REG_B [15:0] $end
$var wire 16 ' REG_A [15:0] $end
$var wire 16 ( REG_7 [15:0] $end
$var wire 16 ) REG_6 [15:0] $end
$var wire 16 * REG_5 [15:0] $end
$var wire 16 + REG_4 [15:0] $end
$var wire 16 , REG_3 [15:0] $end
$var wire 16 - REG_2 [15:0] $end
$var wire 16 . REG_1 [15:0] $end
$var wire 16 / REG_0 [15:0] $end
$var wire 1 0 RAM_WEN $end
$var wire 16 1 RAM_OUT [15:0] $end
$var wire 16 2 RAM_IN [15:0] $end
$var wire 8 3 RAM_ADDR [7:0] $end
$var wire 16 4 RAM_7 [15:0] $end
$var wire 16 5 RAM_6 [15:0] $end
$var wire 16 6 RAM_5 [15:0] $end
$var wire 16 7 RAM_4 [15:0] $end
$var wire 16 8 RAM_3 [15:0] $end
$var wire 16 9 RAM_2 [15:0] $end
$var wire 16 : RAM_1 [15:0] $end
$var wire 16 ; RAM_0 [15:0] $end
$var wire 8 < P_COUNT [7:0] $end
$var wire 15 = PROM_OUT [14:0] $end
$var wire 8 > OP_DATA [7:0] $end
$var wire 4 ? OP_CODE [3:0] $end
$var wire 3 @ N_REG_B [2:0] $end
$var wire 3 A N_REG_A [2:0] $end
$var wire 16 B IO64_OUT [15:0] $end
$var wire 1 C CLK_WB $end
$var wire 1 D CLK_FT $end
$var wire 1 E CLK_EX $end
$var wire 1 F CLK_DC $end
$scope module C1 $end
$var wire 1 ! CLK $end
$var reg 1 F CLK_DC $end
$var reg 1 E CLK_EX $end
$var reg 1 D CLK_FT $end
$var reg 1 C CLK_WB $end
$var reg 2 G COUNT [1:0] $end
$upscope $end
$scope module C2 $end
$var wire 1 D CLK_FT $end
$var wire 8 H P_COUNT [7:0] $end
$var reg 15 I PROM_OUT [14:0] $end
$var reg 240 J mem [239:0] $end
$upscope $end
$scope module C3 $end
$var wire 1 F CLK_DC $end
$var wire 15 K PROM_OUT [14:0] $end
$var reg 4 L OP_CODE [3:0] $end
$var reg 8 M OP_DATA [7:0] $end
$upscope $end
$scope module C4 $end
$var wire 1 F CLK_DC $end
$var wire 3 N N_REG_IN [2:0] $end
$var wire 16 O REG_7 [15:0] $end
$var wire 16 P REG_6 [15:0] $end
$var wire 16 Q REG_5 [15:0] $end
$var wire 16 R REG_4 [15:0] $end
$var wire 16 S REG_3 [15:0] $end
$var wire 16 T REG_2 [15:0] $end
$var wire 16 U REG_1 [15:0] $end
$var wire 16 V REG_0 [15:0] $end
$var reg 3 W N_REG_OUT [2:0] $end
$var reg 16 X REG_OUT [15:0] $end
$upscope $end
$scope module C5 $end
$var wire 1 F CLK_DC $end
$var wire 3 Y N_REG_IN [2:0] $end
$var wire 16 Z REG_7 [15:0] $end
$var wire 16 [ REG_6 [15:0] $end
$var wire 16 \ REG_5 [15:0] $end
$var wire 16 ] REG_4 [15:0] $end
$var wire 16 ^ REG_3 [15:0] $end
$var wire 16 _ REG_2 [15:0] $end
$var wire 16 ` REG_1 [15:0] $end
$var wire 16 a REG_0 [15:0] $end
$var reg 3 b N_REG_OUT [2:0] $end
$var reg 16 c REG_OUT [15:0] $end
$upscope $end
$scope module C6 $end
$var wire 1 F CLK_DC $end
$var wire 16 d IO65_IN [15:0] $end
$var wire 8 e RAM_AD_IN [7:0] $end
$var wire 16 f RAM_7 [15:0] $end
$var wire 16 g RAM_6 [15:0] $end
$var wire 16 h RAM_5 [15:0] $end
$var wire 16 i RAM_4 [15:0] $end
$var wire 16 j RAM_3 [15:0] $end
$var wire 16 k RAM_2 [15:0] $end
$var wire 16 l RAM_1 [15:0] $end
$var wire 16 m RAM_0 [15:0] $end
$var reg 8 n RAM_AD_OUT [7:0] $end
$var reg 16 o RAM_OUT [15:0] $end
$upscope $end
$scope module C7 $end
$var wire 1 E CLK_EX $end
$var wire 4 p OP_CODE [3:0] $end
$var wire 8 q OP_DATA [7:0] $end
$var wire 16 r RAM_OUT [15:0] $end
$var wire 16 s REG_A [15:0] $end
$var wire 16 t REG_B [15:0] $end
$var wire 1 # RESET_N $end
$var reg 1 u CMP_FLAG $end
$var reg 8 v P_COUNT [7:0] $end
$var reg 16 w RAM_IN [15:0] $end
$var reg 1 0 RAM_WEN $end
$var reg 16 x REG_IN [15:0] $end
$var reg 1 $ REG_WEN $end
$upscope $end
$scope module C8 $end
$var wire 1 C CLK_WB $end
$var wire 3 y N_REG [2:0] $end
$var wire 16 z REG_IN [15:0] $end
$var wire 1 $ REG_WEN $end
$var wire 1 # RESET_N $end
$var reg 16 { REG_0 [15:0] $end
$var reg 16 | REG_1 [15:0] $end
$var reg 16 } REG_2 [15:0] $end
$var reg 16 ~ REG_3 [15:0] $end
$var reg 16 !" REG_4 [15:0] $end
$var reg 16 "" REG_5 [15:0] $end
$var reg 16 #" REG_6 [15:0] $end
$var reg 16 $" REG_7 [15:0] $end
$upscope $end
$scope module C9 $end
$var wire 1 C CLK_WB $end
$var wire 8 %" RAM_ADDR [7:0] $end
$var wire 16 &" RAM_IN [15:0] $end
$var wire 1 0 RAM_WEN $end
$var reg 16 '" IO64_OUT [15:0] $end
$var reg 16 (" RAM_0 [15:0] $end
$var reg 16 )" RAM_1 [15:0] $end
$var reg 16 *" RAM_2 [15:0] $end
$var reg 16 +" RAM_3 [15:0] $end
$var reg 16 ," RAM_4 [15:0] $end
$var reg 16 -" RAM_5 [15:0] $end
$var reg 16 ." RAM_6 [15:0] $end
$var reg 16 /" RAM_7 [15:0] $end
$upscope $end
$upscope $end
$upscope $end
$enddefinitions $end
#0
$dumpvars
b0 /"
b0 ."
b0 -"
b0 ,"
b0 +"
b0 *"
b0 )"
b0 ("
b0 '"
b0 &"
bx %"
bx $"
bx #"
bx ""
bx !"
bx ~
bx }
bx |
bx {
b0 z
bx y
b0 x
b0 w
b0 v
0u
bx t
bx s
bx r
bx q
bx p
bx o
bx n
b0 m
b0 l
b0 k
b0 j
b0 i
b0 h
b0 g
b0 f
bx e
b0 d
bx c
bx b
bx a
bx `
bx _
bx ^
bx ]
bx \
bx [
bx Z
bx Y
bx X
bx W
bx V
bx U
bx T
bx S
bx R
bx Q
bx P
bx O
bx N
bx M
bx L
bx K
b100100000000000100000000000000100100100000000100000100000001100101000000000100001000000000100101100000000100001100001010000101000100000000100001000000111000001000000101001001100000101100000001110110000000001000111100000000000000000000000000 J
bx I
b0 H
b0 G
0F
0E
0D
0C
b0 B
bx A
bx @
bx ?
bx >
bx =
b0 <
b0 ;
b0 :
b0 9
b0 8
b0 7
b0 6
b0 5
b0 4
bx 3
b0 2
bx 1
00
bx /
bx .
bx -
bx ,
bx +
bx *
bx )
bx (
bx '
bx &
b0 %
0$
0#
b0 "
0!
$end
#10
b0 e
b0 Y
b0 N
b100100000000000 =
b100100000000000 I
b100100000000000 K
1D
b1 G
1!
#20
0!
#30
b0 >
b0 M
b0 q
b1001 ?
b1001 L
b1001 p
b0 A
b0 W
b0 y
b0 @
b0 b
b0 1
b0 o
b0 r
b0 3
b0 n
b0 %"
1F
0D
b10 G
1!
#40
0!
#50
1E
0F
b11 G
1!
#60
0!
#70
b0 (
b0 O
b0 Z
b0 $"
b0 )
b0 P
b0 [
b0 #"
b0 *
b0 Q
b0 \
b0 ""
b0 +
b0 R
b0 ]
b0 !"
b0 ,
b0 S
b0 ^
b0 ~
b0 -
b0 T
b0 _
b0 }
b0 .
b0 U
b0 `
b0 |
b0 /
b0 V
b0 a
b0 {
1C
0E
b0 G
1!
#80
0!
#90
0C
1D
b1 G
1!
#100
0!
1#
#110
b0 &
b0 c
b0 t
b0 '
b0 X
b0 s
1F
0D
b10 G
1!
#120
0!
#130
b1 <
b1 H
b1 v
1$
1E
0F
b11 G
1!
#140
0!
#150
1C
0E
b0 G
1!
#160
0!
#170
b100000000000000 =
b100000000000000 I
b100000000000000 K
0C
1D
b1 G
1!
#180
0!
#190
b1000 ?
b1000 L
b1000 p
1F
0D
b10 G
1!
#200
0!
#210
b10 <
b10 H
b10 v
1E
0F
b11 G
1!
#220
0!
#230
1C
0E
b0 G
1!
#240
0!
#250
b1 N
b100100100000000 =
b100100100000000 I
b100100100000000 K
0C
1D
b1 G
1!
#260
0!
#270
b1 A
b1 W
b1 y
b1001 ?
b1001 L
b1001 p
1F
0D
b10 G
1!
#280
0!
#290
b11 <
b11 H
b11 v
1E
0F
b11 G
1!
#300
0!
#310
1C
0E
b0 G
1!
#320
0!
#330
b1 e
b100000100000001 =
b100000100000001 I
b100000100000001 K
0C
1D
b1 G
1!
#340
0!
#350
b1 >
b1 M
b1 q
b1000 ?
b1000 L
b1000 p
b1 3
b1 n
b1 %"
1F
0D
b10 G
1!
#360
0!
#370
b100 <
b100 H
b100 v
b1 %
b1 x
b1 z
1E
0F
b11 G
1!
#380
0!
#390
b1 .
b1 U
b1 `
b1 |
1C
0E
b0 G
1!
#400
0!
#410
b0 e
b10 N
b100101000000000 =
b100101000000000 I
b100101000000000 K
0C
1D
b1 G
1!
#420
0!
#430
b0 3
b0 n
b0 %"
b10 A
b10 W
b10 y
b0 >
b0 M
b0 q
b1001 ?
b1001 L
b1001 p
1F
0D
b10 G
1!
#440
0!
#450
b101 <
b101 H
b101 v
b0 %
b0 x
b0 z
1E
0F
b11 G
1!
#460
0!
#470
1C
0E
b0 G
1!
#480
0!
#490
b100001000000000 =
b100001000000000 I
b100001000000000 K
0C
1D
b1 G
1!
#500
0!
#510
b1000 ?
b1000 L
b1000 p
1F
0D
b10 G
1!
#520
0!
#530
b110 <
b110 H
b110 v
1E
0F
b11 G
1!
#540
0!
#550
1C
0E
b0 G
1!
#560
0!
#570
b11 N
b100101100000000 =
b100101100000000 I
b100101100000000 K
0C
1D
b1 G
1!
#580
0!
#590
b11 A
b11 W
b11 y
b1001 ?
b1001 L
b1001 p
1F
0D
b10 G
1!
#600
0!
#610
b111 <
b111 H
b111 v
1E
0F
b11 G
1!
#620
0!
#630
1C
0E
b0 G
1!
#640
0!
#650
b1010 e
b100001100001010 =
b100001100001010 I
b100001100001010 K
0C
1D
b1 G
1!
#660
0!
#670
b1010 >
b1010 M
b1010 q
b1000 ?
b1000 L
b1000 p
b1111111111111111 1
b1111111111111111 o
b1111111111111111 r
b1010 3
b1010 n
b1010 %"
1F
0D
b10 G
1!
#680
0!
#690
b1000 <
b1000 H
b1000 v
b1010 %
b1010 x
b1010 z
1E
0F
b11 G
1!
#700
0!
#710
b1010 ,
b1010 S
b1010 ^
b1010 ~
1C
0E
b0 G
1!
#720
0!
#730
b100000 e
b1 Y
b10 N
b101000100000 =
b101000100000 I
b101000100000 K
0C
1D
b1 G
1!
#740
0!
#750
b100000 3
b100000 n
b100000 %"
b1 &
b1 c
b1 t
b1 @
b1 b
b10 A
b10 W
b10 y
b100000 >
b100000 M
b100000 q
b1 ?
b1 L
b1 p
1F
0D
b10 G
1!
#760
0!
#770
b1001 <
b1001 H
b1001 v
b1 %
b1 x
b1 z
1E
0F
b11 G
1!
#780
0!
#790
b1 -
b1 T
b1 _
b1 }
1C
0E
b0 G
1!
#800
0!
#810
b1000000 e
b10 Y
b0 N
b100001000000 =
b100001000000 I
b100001000000 K
0C
1D
b1 G
1!
#820
0!
#830
b1000000 >
b1000000 M
b1000000 q
b0 A
b0 W
b0 y
b10 @
b10 b
b0 1
b0 o
b0 r
b1000000 3
b1000000 n
b1000000 %"
1F
0D
b10 G
1!
#840
0!
#850
b1010 <
b1010 H
b1010 v
1E
0F
b11 G
1!
#860
0!
#870
b1 /
b1 V
b1 a
b1 {
1C
0E
b0 G
1!
#880
0!
#890
b111000001000000 =
b111000001000000 I
b111000001000000 K
0C
1D
b1 G
1!
#900
0!
#910
b1 '
b1 X
b1 s
b1110 ?
b1110 L
b1110 p
1F
0D
b10 G
1!
#920
0!
#930
b1011 <
b1011 H
b1011 v
10
0$
b1 2
b1 w
b1 &"
1E
0F
b11 G
1!
#940
0!
#950
b1 B
b1 '"
1C
0E
b0 G
1!
#960
0!
#970
b1100000 e
b11 Y
b10 N
b101001001100000 =
b101001001100000 I
b101001001100000 K
0C
1D
b1 G
1!
#980
0!
#990
b1100000 >
b1100000 M
b1100000 q
b1010 ?
b1010 L
b1010 p
b10 A
b10 W
b10 y
b1010 &
b1010 c
b1010 t
b11 @
b11 b
b1111111111111111 1
b1111111111111111 o
b1111111111111111 r
b1100000 3
b1100000 n
b1100000 %"
1F
0D
b10 G
1!
#1000
0!
#1010
b1100 <
b1100 H
b1100 v
00
1E
0F
b11 G
1!
#1020
0!
#1030
1C
0E
b0 G
1!
#1040
0!
#1050
b1110 e
b0 Y
b0 N
b101100000001110 =
b101100000001110 I
b101100000001110 K
0C
1D
b1 G
1!
#1060
0!
#1070
b1110 3
b1110 n
b1110 %"
b1 &
b1 c
b1 t
b0 @
b0 b
b0 A
b0 W
b0 y
b1110 >
b1110 M
b1110 q
b1011 ?
b1011 L
b1011 p
1F
0D
b10 G
1!
#1080
0!
#1090
b1101 <
b1101 H
b1101 v
1E
0F
b11 G
1!
#1100
0!
#1110
1C
0E
b0 G
1!
#1120
0!
#1130
b1000 e
b110000000001000 =
b110000000001000 I
b110000000001000 K
0C
1D
b1 G
1!
#1140
0!
#1150
b1000 >
b1000 M
b1000 q
b1100 ?
b1100 L
b1100 p
b1000 3
b1000 n
b1000 %"
1F
0D
b10 G
1!
#1160
0!
#1170
b1000 <
b1000 H
b1000 v
1E
0F
b11 G
1!
#1180
0!
#1190
1C
0E
b0 G
1!
#1200
0!
#1210
b100000 e
b1 Y
b10 N
b101000100000 =
b101000100000 I
b101000100000 K
0C
1D
b1 G
1!
#1220
0!
#1230
b100000 3
b100000 n
b100000 %"
b1 @
b1 b
b10 A
b10 W
b10 y
b100000 >
b100000 M
b100000 q
b1 ?
b1 L
b1 p
1F
0D
b10 G
1!
#1240
0!
#1250
b1001 <
b1001 H
b1001 v
1$
b10 %
b10 x
b10 z
1E
0F
b11 G
1!
#1260
0!
#1270
b10 -
b10 T
b10 _
b10 }
1C
0E
b0 G
1!
#1280
0!
#1290
b1000000 e
b10 Y
b0 N
b100001000000 =
b100001000000 I
b100001000000 K
0C
1D
b1 G
1!
#1300
0!
